josecythoncompiler/compiler.cp311-win_amd64.pyd
josecythoncompiler-0.2.dist-info/METADATA
josecythoncompiler-0.2.dist-info/WHEEL
josecythoncompiler-0.2.dist-info/top_level.txt
josecythoncompiler-0.2.dist-info/RECORD
