Metadata-Version: 2.1
Name: josecythoncompiler
Version: 0.2
Summary: Um projeto simples usando Cython.
Author: Jose Eduardo
Author-email: josedumoura@exgmail.com
Classifier: Programming Language :: Python :: 3
Classifier: License :: OSI Approved :: MIT License
Classifier: Operating System :: OS Independent
Requires-Python: >=3.6
